scpair/__init__.py
scpair/evaluator.py
scpair/loss.py
scpair/model.py
scpair/pairedVAE.py
scpair/scVI_distribution.py
scpair/utils.py
scpair-0.1.0.dist-info/LICENSE
scpair-0.1.0.dist-info/METADATA
scpair-0.1.0.dist-info/WHEEL
scpair-0.1.0.dist-info/top_level.txt
scpair-0.1.0.dist-info/RECORD
