Metadata-Version: 2.1
Name: scpair
Version: 0.1.0
Summary: scPair: boosting single cell multimodal analysis by leveraging implicit feature selection and single cell atlases
Author: Hongru Hu, Gerald Quon
Author-email: hrhu@ucdavis.edu
License: MIT
Project-URL: Homepage, https://github.com/quon-titative-biology/scPair
Project-URL: Repository, https://github.com/quon-titative-biology/scPair
Project-URL: Documentation, https://github.com/quon-titative-biology/scPair/blob/main/tutorials/README.md
Project-URL: Bug Tracker, https://github.com/quon-titative-biology/scPair/issues
Keywords: single-cell,multimodal,scRNA-seq,ATAC-seq,deep-learning,bioinformatics,genomics,machine-learning,neural-networks
Classifier: Development Status :: 4 - Beta
Classifier: Intended Audience :: Science/Research
Classifier: Programming Language :: Python :: 3
Classifier: Programming Language :: Python :: 3.10
Classifier: Programming Language :: Python :: 3.11
Classifier: Topic :: Scientific/Engineering :: Bio-Informatics
Classifier: Topic :: Scientific/Engineering :: Artificial Intelligence
Classifier: Operating System :: OS Independent
Requires-Python: >=3.10,<3.13
License-File: LICENSE
Requires-Dist: numpy>=1.21.0
Requires-Dist: pandas>=1.3.0
Requires-Dist: scipy>=1.7.0
Requires-Dist: scikit-learn>=1.0.0
Requires-Dist: matplotlib>=3.5.0
Requires-Dist: seaborn>=0.11.0
Requires-Dist: plotly>=5.0.0
Requires-Dist: scanpy>=1.8.0
Requires-Dist: anndata>=0.8.0
Requires-Dist: torch>=2.0.0
Requires-Dist: torchvision>=0.15.0
Requires-Dist: triton<3.0.0,>=2.0.0
Requires-Dist: tqdm>=4.60.0
Requires-Dist: jupyter>=1.0.0
Requires-Dist: ipywidgets>=7.6.0
Provides-Extra: cuda
Requires-Dist: torch==2.0.1; extra == "cuda"
Requires-Dist: torchaudio==2.0.2; extra == "cuda"
Requires-Dist: torchmetrics==1.3.2; extra == "cuda"
Requires-Dist: torchvision==0.15.2; extra == "cuda"
